spylib/__init__.py
spylib/admin_api.py
spylib/constants.py
spylib/exceptions.py
spylib/fastapi_extensions/__init__.py
spylib/fastapi_extensions/authentication.py
spylib/hmac.py
spylib/multipass.py
spylib/oauth/__init__.py
spylib/oauth/callback.py
spylib/oauth/exchange_token.py
spylib/oauth/fastapi.py
spylib/oauth/models.py
spylib/oauth/redirects.py
spylib/oauth/signature_validation.py
spylib/oauth/tokens.py
spylib/oauth/validations.py
spylib/py.typed
spylib/session_token.py
spylib/utils/__init__.py
spylib/utils/domain.py
spylib/utils/httpclient.py
spylib/utils/jwtoken.py
spylib/utils/misc.py
spylib/utils/rest.py
spylib/utils/shortuuid.py
spylib/webhook/__init__.py
spylib/webhook/graphql_queries.py
spylib-0.10.6.dist-info/METADATA
spylib-0.10.6.dist-info/WHEEL
spylib-0.10.6.dist-info/licenses/LICENSE
spylib-0.10.6.dist-info/RECORD
