Metadata-Version: 2.4
Name: spylib
Version: 0.10.6
Summary: A library to facilitate interfacing with Shopify's API
License: MIT
License-File: LICENSE
Author: Anthony Hillairet
Author-email: ant@satel.ca
Maintainer: Anthony Hillairet
Maintainer-email: ant@satel.ca
Requires-Python: >=3.9,<4.0
Classifier: License :: OSI Approved :: MIT License
Classifier: Programming Language :: Python :: 3
Classifier: Programming Language :: Python :: 3.9
Classifier: Programming Language :: Python :: 3.10
Classifier: Programming Language :: Python :: 3.11
Classifier: Programming Language :: Python :: 3.12
Classifier: Programming Language :: Python :: 3.13
Classifier: Programming Language :: Python :: 3.14
Provides-Extra: fastapi
Requires-Dist: PyJWT (>=2.1.0,<3.0.0)
Requires-Dist: fastapi (>=0.100.0) ; extra == "fastapi"
Requires-Dist: httpx (>=0.18.1,<=0.24.1)
Requires-Dist: pycryptodome (>=3.10.1,<4.0.0)
Requires-Dist: pydantic (>=2.5.2,<3.0.0)
Requires-Dist: starlette (>=0.15.0)
Requires-Dist: tenacity (>=8.2.2,<9.0.0)
Project-URL: Homepage, https://satelcreative.github.io/spylib
Project-URL: Repository, https://github.com/SatelCreative/spylib
